odoo/addons/account_move_auto_post_ref/README.rst
odoo/addons/account_move_auto_post_ref/__init__.py
odoo/addons/account_move_auto_post_ref/__manifest__.py
odoo/addons/account_move_auto_post_ref/i18n/account_move_auto_post_ref.pot
odoo/addons/account_move_auto_post_ref/i18n/it.po
odoo/addons/account_move_auto_post_ref/models/__init__.py
odoo/addons/account_move_auto_post_ref/models/account_move.py
odoo/addons/account_move_auto_post_ref/readme/CONTRIBUTORS.md
odoo/addons/account_move_auto_post_ref/readme/DESCRIPTION.md
odoo/addons/account_move_auto_post_ref/readme/USAGE.md
odoo/addons/account_move_auto_post_ref/static/description/icon.png
odoo/addons/account_move_auto_post_ref/static/description/index.html
odoo/addons/account_move_auto_post_ref/tests/__init__.py
odoo/addons/account_move_auto_post_ref/tests/test_invoice.py
odoo_addon_account_move_auto_post_ref-18.0.1.0.1.dist-info/METADATA
odoo_addon_account_move_auto_post_ref-18.0.1.0.1.dist-info/WHEEL
odoo_addon_account_move_auto_post_ref-18.0.1.0.1.dist-info/top_level.txt
odoo_addon_account_move_auto_post_ref-18.0.1.0.1.dist-info/RECORD
